khash/siphash.cpython-39-aarch64-linux-gnu.so
khash/khash.cpython-39-aarch64-linux-gnu.so
khash/__init__.py
khash/tree.cpython-39-aarch64-linux-gnu.so
khash/container.cpython-39-aarch64-linux-gnu.so
khash/aim_storage/containertreeview.py
khash/aim_storage/prefixcontainer.py
khash/aim_storage/treearrayview.py
khash/aim_storage/__init__.py
khash/aim_storage/container.py
khash-0.6.0.dist-info/top_level.txt
khash-0.6.0.dist-info/METADATA
khash-0.6.0.dist-info/LICENSE.md
khash-0.6.0.dist-info/WHEEL
khash-0.6.0.dist-info/RECORD
