Metadata-Version: 2.1
Name: khash
Version: 0.6.0
Summary: KHASH implementation
License: Proprietary
License-File: LICENSE.md
